INSTALL.txt
LICENSE.txt
MANIFEST.in
README
setup.py
data/e-2.txt
data/testdata_irregular.txt
data/testdata_large.txt
data/testdata_numerical.txt
data/testdata_words.txt
docs/source/sphinxext/LICENSE.txt
docs/source/sphinxext/README.txt
pyanno/__init__.py
pyanno/abstract_model.py
pyanno/annotations.py
pyanno/database.py
pyanno/modelA.py
pyanno/modelB.py
pyanno/modelBt.py
pyanno/modelBt_loopdesign.py
pyanno/models.py
pyanno/sampling.py
pyanno/util.py
pyanno.egg-info/PKG-INFO
pyanno.egg-info/SOURCES.txt
pyanno.egg-info/dependency_links.txt
pyanno.egg-info/entry_points.txt
pyanno.egg-info/top_level.txt
pyanno.egg-info/inst/appinst.dat
pyanno.egg-info/inst/folder.ico
pyanno.egg-info/prefix/pyAnno_data/.DS_Store
pyanno.egg-info/prefix/pyAnno_data/README
pyanno.egg-info/prefix/pyAnno_data/e-2.txt
pyanno.egg-info/prefix/pyAnno_data/testdata_irregular.txt
pyanno.egg-info/prefix/pyAnno_data/testdata_large.txt
pyanno.egg-info/prefix/pyAnno_data/testdata_numerical.txt
pyanno.egg-info/prefix/pyAnno_data/testdata_words.txt
pyanno/measures/__init__.py
pyanno/measures/agreement.py
pyanno/measures/covariation.py
pyanno/measures/distances.py
pyanno/measures/helpers.py
pyanno/plots/__init__.py
pyanno/plots/annotations_plot.py
pyanno/plots/hinton_plot.py
pyanno/plots/matrix_plot.py
pyanno/plots/plot_tools.py
pyanno/plots/plots_superclass.py
pyanno/plots/pyanno_plots.py
pyanno/plots/theta_plot.py
pyanno/plots/theta_tensor_plot.py
pyanno/test/__init__.py
pyanno/test/test_annotations.py
pyanno/test/test_database.py
pyanno/test/test_measures.py
pyanno/test/test_modelA.py
pyanno/test/test_modelB.py
pyanno/test/test_modelBt.py
pyanno/test/test_modelBt_loopdesign.py
pyanno/test/test_sampling.py
pyanno/test/test_util.py
pyanno/ui/__init__.py
pyanno/ui/annotation_stat_view.py
pyanno/ui/annotations_view.py
pyanno/ui/arrayview.py
pyanno/ui/database_view.py
pyanno/ui/debug_model_view.py
pyanno/ui/main.py
pyanno/ui/model_a_view.py
pyanno/ui/model_b_view.py
pyanno/ui/model_bt_view.py
pyanno/ui/model_btloop_view.py
pyanno/ui/model_data_view.py
pyanno/ui/model_view.py
pyanno/ui/parameters_tabular_viewer.py
pyanno/ui/posterior_view.py
pyanno/ui/pyanno_ui_application.py
pyanno/ui/appbase/__init__.py
pyanno/ui/appbase/long_running_call.py
pyanno/ui/appbase/pulse_progress_dialog.py
pyanno/ui/appbase/wx_utils.py