Metadata-Version: 1.0
Name: pyanno
Version: 2.0.1
Summary: Package for curating data annotation efforts.
Home-page: https://github.com/enthought/uchicago-pyanno
Author: UNKNOWN
Author-email: UNKNOWN
License: BSD
Download-URL: https://github.com/enthought/uchicago-pyanno
Platform: Any
